crypto_component/__init__.py
crypto_component/encryption/__init__.py
crypto_component/encryption/aes.py
crypto_component/encryption/ecdsa.py
crypto_component/encryption/ecies.py
crypto_component/exception/__init__.py
crypto_component/exception/crypto_exception.py
crypto_component/hash/__init__.py
crypto_component/hash/digest.py
crypto_component/kdf/__init__.py
crypto_component/kdf/kdf.py
crypto_component/signature/__init__.py
crypto_component/utils/__init__.py
crypto_component/utils/handle_crypto.py
crypto_component/utils/handle_data.py
ontology_ddxf_crypto-0.0.2.dist-info/METADATA
ontology_ddxf_crypto-0.0.2.dist-info/RECORD
ontology_ddxf_crypto-0.0.2.dist-info/WHEEL
ontology_ddxf_crypto-0.0.2.dist-info/entry_points.txt
ontology_ddxf_crypto-0.0.2.dist-info/top_level.txt
