Metadata-Version: 2.1
Name: ontology-ddxf-crypto
Version: 0.0.2
Summary: Ontology DDXF Cryptography Components
Home-page: https://github.com/NashMiao/ontology-ddxf-crypto
Author: NashMiao
Author-email: wdx7266@outlook.com
Maintainer: NashMiao
Maintainer-email: wdx7266@outlook.com
License: GNU Lesser General Public License v3 (LGPLv3)
Platform: UNKNOWN
Classifier: Development Status :: 2 - Pre-Alpha
Classifier: Intended Audience :: Developers
Classifier: License :: OSI Approved :: GNU Lesser General Public License v3 (LGPLv3)
Classifier: Natural Language :: English
Classifier: Programming Language :: Python :: 3.5
Classifier: Programming Language :: Python :: 3.6
Classifier: Programming Language :: Python :: 3.7
Requires-Python: >=3.5,<4
Requires-Dist: ecdsa
Requires-Dist: pycryptodomex
Requires-Dist: ontology-python-sdk
